LICENSE
README.md
dameimgs.py
damejson.py
damerss.py
dameserver.py
dameurls.py
setup.py
testsbycommands.sh
damewebutils.egg-info/PKG-INFO
damewebutils.egg-info/SOURCES.txt
damewebutils.egg-info/dependency_links.txt
damewebutils.egg-info/not-zip-safe
damewebutils.egg-info/requires.txt
damewebutils.egg-info/top_level.txt
damewebutils/app/TCPClient.py
damewebutils/app/TCPServer.py
damewebutils/files/document.xml
damewebutils/files/foaf.rdf
damewebutils/files/index.xhtml
damewebutils/files/items.xml
damewebutils/files/output.xhtml
damewebutils/files/rss.xml
damewebutils/files/source.xml
damewebutils/files/tree_created.xml
damewebutils/files//tests/damegender-imgs.txt
damewebutils/files//tests/damegender-rss.txt
damewebutils/files//tests/dameimgs.txt
damewebutils/files//tests/data3.txt
damewebutils/files//tests/davidam-index.txt
damewebutils/files//tests/github-davidam.txt
damewebutils/files//tests/template.txt
damewebutils/files/tests/damegender-imgs.txt
damewebutils/files/tests/damegender-rss.txt
damewebutils/files/tests/dameimgs.txt
damewebutils/files/tests/data3.txt
damewebutils/files/tests/davidam-index.txt
damewebutils/files/tests/github-davidam.txt
damewebutils/files/tests/template.txt
damewebutils/tests/test_cookies.py
damewebutils/tests/test_requests.py
damewebutils/tests/test_wikidata.py
damewebutils/tests/test_xml.py