Metadata-Version: 2.1
Name: damewebutils
Version: 0.2.3
Summary: Web utils for Python
Home-page: http://github.com/davidam/damewebutils
Author: David Arroyo Menéndez
Author-email: davidam@gmail.com
License: GPLv3
Keywords: web,links
Classifier: Development Status :: 3 - Alpha
Classifier: License :: OSI Approved :: GNU General Public License v3 (GPLv3)
Classifier: Programming Language :: Python :: 3.6
Classifier: Topic :: Text Processing :: Linguistic
License-File: LICENSE
